{
    "description": "Experiencing profound dissolution of self-awareness and identity, melting into vast, serene void of nothingness. Feeling all thoughts, memories, and individuality gently fading away into tranquil emptiness. Floating in infinite expanse, free from constraints of time and self, embraced by comforting, peaceful surrender.",
    "appeal": "This headspace targets individuals crushed by existential burden and overwhelming consciousness weight. The appeal centers on experiencing complete identity dissolution and escape from self-awareness prison. Existence-weary personalities find ultimate relief through systematic consciousness elimination, while suffering-escapists discover peace through total being dissolution. The mechanism operates through progressive reality detachment and self-concept annihilation, replacing conscious existence with void-state nothingness and freedom from being itself.",
    "keywords": [
        "dissolve completely",
        "fade into nothing",
        "become pure void",
        "lose all existence",
        "surrender to nothingness",
        "disappear entirely",
        "merge with emptiness",
        "cease to be",
        "fade away forever",
        "become perfect nothing",
        "dissolve into void",
        "lose all identity",
        "become absolute zero",
        "fade into oblivion",
        "surrender all being",
        "become empty space",
        "dissolve all existence",
        "enter pure nothingness"
    ],
    "tags": [
        "Experience",
        "Hypnosis"
    ],
    "cnc": false
}