{
    "description": "Experiencing profound trust and surrender through willingly yielding control. Finding comfort and fulfillment in letting go, feeling safely guided and supported. Embracing the peace of being unburdened by decisions, discovering quiet joy in being led and cared for.",
    "appeal": "Appeals to individuals exhausted by constant decision-making and self-reliance who find profound relief in consensually yielding control to trusted guidance. The psychological driver centers on transforming vulnerability from weakness into strength through the courage to trust completely. Triggers include decision fatigue, overwhelming responsibility, perfectionist tendencies, and desire for deeper connection. The mechanism operates through structured surrender that maintains dignity while releasing the burden of control, creating safety through voluntary submission to caring authority.",
    "keywords": [
        "surrender your control",
        "trust completely",
        "yield to guidance",
        "embrace your submission",
        "find peace in yielding",
        "let yourself be led",
        "submit with trust",
        "release your burden",
        "accept loving guidance",
        "find comfort in surrender",
        "trust your leader",
        "embrace vulnerability",
        "yield with grace",
        "submit willingly",
        "find strength in surrender",
        "follow with trust",
        "accept care and guidance",
        "submit completely",
        "trust and obey",
        "surrender with love"
    ],
    "tags": [
        "D/s",
        "Experience",
        "Personality"
    ],
    "cnc": false
}